strands_clova/__init__.py
strands_clova/clova.py
strands_clova/py.typed
strands_clova-0.1.2.dist-info/METADATA
strands_clova-0.1.2.dist-info/WHEEL
strands_clova-0.1.2.dist-info/licenses/LICENSE
strands_clova-0.1.2.dist-info/RECORD
