Metadata-Version: 2.4
Name: strands-clova
Version: 0.1.2
Summary: CLOVA Studio model provider for Strands Agents SDK
Project-URL: Homepage, https://github.com/aidendef/strands-clova
Project-URL: Documentation, https://github.com/aidendef/strands-clova#readme
Project-URL: Repository, https://github.com/aidendef/strands-clova
Project-URL: Issues, https://github.com/aidendef/strands-clova/issues
Author-email: aidendef <aiden02095@gmail.com>
License-Expression: MIT
License-File: LICENSE
Keywords: agents,ai,clova,korean,llm,naver,strands
Classifier: Development Status :: 3 - Alpha
Classifier: Intended Audience :: Developers
Classifier: License :: OSI Approved :: MIT License
Classifier: Programming Language :: Python :: 3
Classifier: Programming Language :: Python :: 3.10
Classifier: Programming Language :: Python :: 3.11
Classifier: Programming Language :: Python :: 3.12
Classifier: Topic :: Scientific/Engineering :: Artificial Intelligence
Classifier: Topic :: Software Development :: Libraries :: Python Modules
Requires-Python: >=3.10
Requires-Dist: httpx>=0.27.0
Requires-Dist: pydantic>=2.0.0
Requires-Dist: strands-agents
Provides-Extra: dev
Requires-Dist: black>=23.0.0; extra == 'dev'
Requires-Dist: build>=0.10.0; extra == 'dev'
Requires-Dist: mypy>=1.0.0; extra == 'dev'
Requires-Dist: pytest-asyncio>=0.21.0; extra == 'dev'
Requires-Dist: pytest-cov>=4.0.0; extra == 'dev'
Requires-Dist: pytest-mock>=3.0.0; extra == 'dev'
Requires-Dist: pytest>=7.0.0; extra == 'dev'
Requires-Dist: ruff>=0.1.0; extra == 'dev'
Requires-Dist: twine>=4.0.0; extra == 'dev'
